simulation/blinkers.v
module blinkers (
    input clk,
    input rstbtn,
    output reg led1, led2, led3 = 0
);

    reg clk_edge = 0;

    initial begin
        $dumpfile("../vcd/blinkers.vcd");
        $dumpvars(0, blinkers);

        // $monitor("Time = %0t clk = %0d sig = %0d", $time, clk, clk_edge);
        #1000 $finish;
    end

    always #1 begin 
        #10 clk_edge = ~clk_edge;
    end

    reg [3:0] cycle_count_led1 = 'b0;
    reg [3:0] cycle_count_led2 = 'b0;

    reg [3:0] LED_1_BLINK_INTERVAL = 'b1010; // 10
    reg [3:0] LED_2_BLINK_INTERVAL = 'b0101; // 5

    // TODO - led 3 on randomized interval

    task cycle_led (
        output led,
        input reg [3:0] blink_interval,
        inout reg [3:0] cycle_count
    );
        if (cycle_count > 0 && cycle_count % blink_interval == 0) begin
            cycle_count = 0;
            led = 1;
        end else begin
            $display("[$display]: Cycle Task: Cycle Count: %d, Blink Interval: %d", cycle_count, blink_interval);
            cycle_count += 1;
            led = 0;
        end
    endtask

    always @(posedge clk_edge) begin
        if (rstbtn) begin 
            led1 = 0;
            led2 = 0;
            led3 = 0;
            cycle_count_led1 = 0;
            cycle_count_led2 = 0;
        end else begin 
            cycle_led(led1, LED_1_BLINK_INTERVAL, cycle_count_led1);
            cycle_led(led2, LED_2_BLINK_INTERVAL, cycle_count_led2);
        end
    end
endmodule

vcd/blinkers.vcd
$date
	Tue Jul 22 10:56:08 2025
$end
$version
	Icarus Verilog
$end
$timescale
	1s
$end
$scope module blinkers $end
$var wire 1 ! clk $end
$var wire 1 " rstbtn $end
$var reg 4 # LED_1_BLINK_INTERVAL [3:0] $end
$var reg 4 $ LED_2_BLINK_INTERVAL [3:0] $end
$var reg 1 % clk_edge $end
$var reg 4 & cycle_count_led1 [3:0] $end
$var reg 4 ' cycle_count_led2 [3:0] $end
$var reg 1 ( led1 $end
$var reg 1 ) led2 $end
$var reg 1 * led3 $end
$scope task cycle_led $end
$var reg 4 + blink_interval [3:0] $end
$var reg 4 , cycle_count [3:0] $end
$var reg 1 - led $end
$upscope $end
$upscope $end
$enddefinitions $end
$comment Show the parameter values. $end
$dumpall
$end
#0
$dumpvars
x-
bx ,
bx +
0*
x)
x(
b0 '
b0 &
0%
b101 $
b1010 #
z"
z!
$end
#11
b1 '
0)
b1 &
0(
0-
b1 ,
b101 +
1%
#22
0%
#33
b10 '
b10 &
b10 ,
b101 +
1%
#44
0%
#55
b11 '
b11 &
b11 ,
b101 +
1%
#66
0%
#77
b100 '
b100 &
b100 ,
b101 +
1%
#88
0%
#99
b101 '
b101 &
b101 ,
b101 +
1%
#110
0%
#121
b0 '
1)
1-
b110 &
b0 ,
b101 +
1%
#132
0%
#143
b1 '
0)
b111 &
0-
b1 ,
b101 +
1%
#154
0%
#165
b10 '
b1000 &
b10 ,
b101 +
1%
#176
0%
#187
b11 '
b1001 &
b11 ,
b101 +
1%
#198
0%
#209
b100 '
b1010 &
b100 ,
b101 +
1%
#220
0%
#231
b101 '
b0 &
1(
0-
b101 ,
b101 +
1%
#242
0%
#253
b0 '
1)
1-
b1 &
0(
b0 ,
b101 +
1%
#264
0%
#275
b1 '
0)
b10 &
0-
b1 ,
b101 +
1%
#286
0%
#297
b10 '
b11 &
b10 ,
b101 +
1%
#308
0%
#319
b11 '
b100 &
b11 ,
b101 +
1%
#330
0%
#341
b100 '
b101 &
b100 ,
b101 +
1%
#352
0%
#363
b101 '
b110 &
b101 ,
b101 +
1%
#374
0%
#385
b0 '
1)
1-
b111 &
b0 ,
b101 +
1%
#396
0%
#407
b1 '
0)
b1000 &
0-
b1 ,
b101 +
1%
#418
0%
#429
b10 '
b1001 &
b10 ,
b101 +
1%
#440
0%
#451
b11 '
b1010 &
b11 ,
b101 +
1%
#462
0%
#473
b100 '
b0 &
1(
0-
b100 ,
b101 +
1%
#484
0%
#495
b101 '
b1 &
0(
b101 ,
b101 +
1%
#506
0%
#517
b0 '
1)
1-
b10 &
b0 ,
b101 +
1%
#528
0%
#539
b1 '
0)
b11 &
0-
b1 ,
b101 +
1%
#550
0%
#561
b10 '
b100 &
b10 ,
b101 +
1%
#572
0%
#583
b11 '
b101 &
b11 ,
b101 +
1%
#594
0%
#605
b100 '
b110 &
b100 ,
b101 +
1%
#616
0%
#627
b101 '
b111 &
b101 ,
b101 +
1%
#638
0%
#649
b0 '
1)
1-
b1000 &
b0 ,
b101 +
1%
#660
0%
#671
b1 '
0)
b1001 &
0-
b1 ,
b101 +
1%
#682
0%
#693
b10 '
b1010 &
b10 ,
b101 +
1%
#704
0%
#715
b11 '
b0 &
1(
0-
b11 ,
b101 +
1%
#726
0%
#737
b100 '
b1 &
0(
b100 ,
b101 +
1%
#748
0%
#759
b101 '
b10 &
b101 ,
b101 +
1%
#770
0%
#781
b0 '
1)
1-
b11 &
b0 ,
b101 +
1%
#792
0%
#803
b1 '
0)
b100 &
0-
b1 ,
b101 +
1%
#814
0%
#825
b10 '
b101 &
b10 ,
b101 +
1%
#836
0%
#847
b11 '
b110 &
b11 ,
b101 +
1%
#858
0%
#869
b100 '
b111 &
b100 ,
b101 +
1%
#880
0%
#891
b101 '
b1000 &
b101 ,
b101 +
1%
#902
0%
#913
b0 '
1)
1-
b1001 &
b0 ,
b101 +
1%
#924
0%
#935
b1 '
0)
b1010 &
0-
b1 ,
b101 +
1%
#946
0%
#957
b10 '
b0 &
1(
0-
b10 ,
b101 +
1%
#968
0%
#979
b11 '
b1 &
0(
b11 ,
b101 +
1%
