simulation/blinkers.v
/*
This module is meant as a way for me to learn some basic Verilog and have an 
easily verifiable test bench.

The idea is that 3 LEDs are on a chip
LED 1 : Blink every 10 cycles
LED 2 : Blink every 5 cycles
LED 3 : (TODO) Blink every <random_interval> cycles
        Since verilog does not synthesize $random, one needs to implement a 
        LFSR to get a random value
        https://en.wikipedia.org/wiki/Linear-feedback_shift_register
        https://simplefpga.blogspot.com/2013/02/random-number-generator-in-verilog-fpga.html
*/
module blinkers (
    input clk,
    input rstbtn,
    output reg led1 = 0, led2 = 0, led3 = 0
);

    reg clk_edge = 0;

    initial begin
        $dumpfile("../vcd/blinkers.vcd");
        $dumpvars(0, blinkers);

        #1000 $finish;
    end

    always #10 begin 
        clk_edge = ~clk_edge;
    end

    reg [3:0] cycle_count_led1 = 'b0;
    reg [3:0] cycle_count_led2 = 'b0;

    reg [3:0] LED_1_BLINK_INTERVAL = 'b1001; // 9
    reg [3:0] LED_2_BLINK_INTERVAL = 'b0100; // 4


    reg [1:0][3:0] calcled1;
    reg [1:0][3:0] calcled2;

    // TODO - led 3 on randomized interval

    task cycle_led (
        output led,
        input reg [3:0] blink_interval,
        inout reg [3:0] cycle_count
    );
        if (cycle_count > 0 && cycle_count % blink_interval == 0) begin
            cycle_count = 0;
            led = 1;
        end else begin
            cycle_count += 1;
            led = 0;
        end
    endtask

    always @(posedge clk_edge, negedge clk_edge, posedge rstbtn) begin
        if (rstbtn) begin 
            led1 <= 0;
            led2 <= 0;
            led3 <= 0;
            cycle_count_led1 <= 0;
            cycle_count_led2 <= 0;
        end else begin 
            cycle_led(led1, LED_1_BLINK_INTERVAL, cycle_count_led1);
            cycle_led(led2, LED_2_BLINK_INTERVAL, cycle_count_led2);
        end
    end
endmodule

vcd/blinkers.vcd
$date
	Wed Jul 23 08:56:08 2025
$end
$version
	Icarus Verilog
$end
$timescale
	1s
$end
$scope module blinkers $end
$var wire 1 ! clk $end
$var wire 1 " rstbtn $end
$var reg 4 # LED_1_BLINK_INTERVAL [3:0] $end
$var reg 4 $ LED_2_BLINK_INTERVAL [3:0] $end
$var reg 1 % clk_edge $end
$var reg 4 & cycle_count_led1 [3:0] $end
$var reg 4 ' cycle_count_led2 [3:0] $end
$var reg 1 ( led1 $end
$var reg 1 ) led2 $end
$var reg 1 * led3 $end
$scope task cycle_led $end
$var reg 4 + blink_interval [3:0] $end
$var reg 4 , cycle_count [3:0] $end
$var reg 1 - led $end
$upscope $end
$upscope $end
$enddefinitions $end
$comment Show the parameter values. $end
$dumpall
$end
#0
$dumpvars
x-
bx ,
bx +
0*
0)
0(
b0 '
b0 &
0%
b100 $
b1001 #
z"
z!
$end
#10
b1 '
b1 &
0-
b1 ,
b100 +
1%
#20
b10 '
b10 &
b10 ,
b100 +
0%
#30
b11 '
b11 &
b11 ,
b100 +
1%
#40
b100 '
b100 &
b100 ,
b100 +
0%
#50
b0 '
1)
1-
b101 &
b0 ,
b100 +
1%
#60
b1 '
0)
b110 &
0-
b1 ,
b100 +
0%
#70
b10 '
b111 &
b10 ,
b100 +
1%
#80
b11 '
b1000 &
b11 ,
b100 +
0%
#90
b100 '
b1001 &
b100 ,
b100 +
1%
#100
b0 '
1)
b0 &
1(
1-
b0 ,
b100 +
0%
#110
b1 '
0)
b1 &
0(
0-
b1 ,
b100 +
1%
#120
b10 '
b10 &
b10 ,
b100 +
0%
#130
b11 '
b11 &
b11 ,
b100 +
1%
#140
b100 '
b100 &
b100 ,
b100 +
0%
#150
b0 '
1)
1-
b101 &
b0 ,
b100 +
1%
#160
b1 '
0)
b110 &
0-
b1 ,
b100 +
0%
#170
b10 '
b111 &
b10 ,
b100 +
1%
#180
b11 '
b1000 &
b11 ,
b100 +
0%
#190
b100 '
b1001 &
b100 ,
b100 +
1%
#200
b0 '
1)
b0 &
1(
1-
b0 ,
b100 +
0%
#210
b1 '
0)
b1 &
0(
0-
b1 ,
b100 +
1%
#220
b10 '
b10 &
b10 ,
b100 +
0%
#230
b11 '
b11 &
b11 ,
b100 +
1%
#240
b100 '
b100 &
b100 ,
b100 +
0%
#250
b0 '
1)
1-
b101 &
b0 ,
b100 +
1%
#260
b1 '
0)
b110 &
0-
b1 ,
b100 +
0%
#270
b10 '
b111 &
b10 ,
b100 +
1%
#280
b11 '
b1000 &
b11 ,
b100 +
0%
#290
b100 '
b1001 &
b100 ,
b100 +
1%
#300
b0 '
1)
b0 &
1(
1-
b0 ,
b100 +
0%
#310
b1 '
0)
b1 &
0(
0-
b1 ,
b100 +
1%
#320
b10 '
b10 &
b10 ,
b100 +
0%
#330
b11 '
b11 &
b11 ,
b100 +
1%
#340
b100 '
b100 &
b100 ,
b100 +
0%
#350
b0 '
1)
1-
b101 &
b0 ,
b100 +
1%
#360
b1 '
0)
b110 &
0-
b1 ,
b100 +
0%
#370
b10 '
b111 &
b10 ,
b100 +
1%
#380
b11 '
b1000 &
b11 ,
b100 +
0%
#390
b100 '
b1001 &
b100 ,
b100 +
1%
#400
b0 '
1)
b0 &
1(
1-
b0 ,
b100 +
0%
#410
b1 '
0)
b1 &
0(
0-
b1 ,
b100 +
1%
#420
b10 '
b10 &
b10 ,
b100 +
0%
#430
b11 '
b11 &
b11 ,
b100 +
1%
#440
b100 '
b100 &
b100 ,
b100 +
0%
#450
b0 '
1)
1-
b101 &
b0 ,
b100 +
1%
#460
b1 '
0)
b110 &
0-
b1 ,
b100 +
0%
#470
b10 '
b111 &
b10 ,
b100 +
1%
#480
b11 '
b1000 &
b11 ,
b100 +
0%
#490
b100 '
b1001 &
b100 ,
b100 +
1%
#500
b0 '
1)
b0 &
1(
1-
b0 ,
b100 +
0%
#510
b1 '
0)
b1 &
0(
0-
b1 ,
b100 +
1%
#520
b10 '
b10 &
b10 ,
b100 +
0%
#530
b11 '
b11 &
b11 ,
b100 +
1%
#540
b100 '
b100 &
b100 ,
b100 +
0%
#550
b0 '
1)
1-
b101 &
b0 ,
b100 +
1%
#560
b1 '
0)
b110 &
0-
b1 ,
b100 +
0%
#570
b10 '
b111 &
b10 ,
b100 +
1%
#580
b11 '
b1000 &
b11 ,
b100 +
0%
#590
b100 '
b1001 &
b100 ,
b100 +
1%
#600
b0 '
1)
b0 &
1(
1-
b0 ,
b100 +
0%
#610
b1 '
0)
b1 &
0(
0-
b1 ,
b100 +
1%
#620
b10 '
b10 &
b10 ,
b100 +
0%
#630
b11 '
b11 &
b11 ,
b100 +
1%
#640
b100 '
b100 &
b100 ,
b100 +
0%
#650
b0 '
1)
1-
b101 &
b0 ,
b100 +
1%
#660
b1 '
0)
b110 &
0-
b1 ,
b100 +
0%
#670
b10 '
b111 &
b10 ,
b100 +
1%
#680
b11 '
b1000 &
b11 ,
b100 +
0%
#690
b100 '
b1001 &
b100 ,
b100 +
1%
#700
b0 '
1)
b0 &
1(
1-
b0 ,
b100 +
0%
#710
b1 '
0)
b1 &
0(
0-
b1 ,
b100 +
1%
#720
b10 '
b10 &
b10 ,
b100 +
0%
#730
b11 '
b11 &
b11 ,
b100 +
1%
#740
b100 '
b100 &
b100 ,
b100 +
0%
#750
b0 '
1)
1-
b101 &
b0 ,
b100 +
1%
#760
b1 '
0)
b110 &
0-
b1 ,
b100 +
0%
#770
b10 '
b111 &
b10 ,
b100 +
1%
#780
b11 '
b1000 &
b11 ,
b100 +
0%
#790
b100 '
b1001 &
b100 ,
b100 +
1%
#800
b0 '
1)
b0 &
1(
1-
b0 ,
b100 +
0%
#810
b1 '
0)
b1 &
0(
0-
b1 ,
b100 +
1%
#820
b10 '
b10 &
b10 ,
b100 +
0%
#830
b11 '
b11 &
b11 ,
b100 +
1%
#840
b100 '
b100 &
b100 ,
b100 +
0%
#850
b0 '
1)
1-
b101 &
b0 ,
b100 +
1%
#860
b1 '
0)
b110 &
0-
b1 ,
b100 +
0%
#870
b10 '
b111 &
b10 ,
b100 +
1%
#880
b11 '
b1000 &
b11 ,
b100 +
0%
#890
b100 '
b1001 &
b100 ,
b100 +
1%
#900
b0 '
1)
b0 &
1(
1-
b0 ,
b100 +
0%
#910
b1 '
0)
b1 &
0(
0-
b1 ,
b100 +
1%
#920
b10 '
b10 &
b10 ,
b100 +
0%
#930
b11 '
b11 &
b11 ,
b100 +
1%
#940
b100 '
b100 &
b100 ,
b100 +
0%
#950
b0 '
1)
1-
b101 &
b0 ,
b100 +
1%
#960
b1 '
0)
b110 &
0-
b1 ,
b100 +
0%
#970
b10 '
b111 &
b10 ,
b100 +
1%
#980
b11 '
b1000 &
b11 ,
b100 +
0%
#990
b100 '
b1001 &
b100 ,
b100 +
1%
#1000
b0 '
1)
b0 &
1(
1-
b0 ,
b100 +
0%
