simulation/blinkers.v
/*
This module is meant as a way for me to learn some basic Verilog and have an 
easily verifiable test bench.

The idea is that 3 LEDs are on a chip
LED 1 : Blink every 10 cycles
LED 2 : Blink every 5 cycles
LED 3 : (TODO) Blink every <random_interval> cycles
        Since verilog does not synthesize $random, one needs to implement a 
        LFSR to get a random value
        https://en.wikipedia.org/wiki/Linear-feedback_shift_register
        https://simplefpga.blogspot.com/2013/02/random-number-generator-in-verilog-fpga.html
*/
module blinkers (
    input clk,
    input rstbtn,
    output reg led1 = 0, led2 = 0, led3 = 0
);

    reg clk_edge = 0;

    initial begin
        $dumpfile("../vcd/blinkers.vcd");
        $dumpvars(0, blinkers);

        // $monitor("Time = %0t clk = %0d sig = %0d", $time, clk, clk_edge);
        #1000 $finish;
    end

    always #10 begin 
        clk_edge = ~clk_edge;
    end

    reg [3:0] cycle_count_led1 = 'b0;
    reg [3:0] cycle_count_led2 = 'b0;

    reg [3:0] LED_1_BLINK_INTERVAL = 'b1010; // 10
    reg [3:0] LED_2_BLINK_INTERVAL = 'b0101; // 5

    // TODO - led 3 on randomized interval

    task cycle_led (
        output led,
        input reg [3:0] blink_interval,
        inout reg [3:0] cycle_count
    );
        if (cycle_count > 0 && cycle_count % blink_interval == 0) begin
            cycle_count = 0;
            led = 1;
        end else begin
            // $display("Cycle Task: Cycle Count: %d, Blink Interval: %d", cycle_count, blink_interval);
            cycle_count += 1;
            led = 0;
        end
    endtask

    always @(posedge clk_edge, posedge rstbtn) begin
        if (rstbtn) begin 
            led1 = 0;
            led2 = 0;
            led3 = 0;
            cycle_count_led1 = 0;
            cycle_count_led2 = 0;
        end else begin 
            cycle_led(led1, LED_1_BLINK_INTERVAL, cycle_count_led1);
            cycle_led(led2, LED_2_BLINK_INTERVAL, cycle_count_led2);
        end
    end
endmodule

vcd/blinkers.vcd
$date
	Tue Jul 22 10:27:02 2025
$end
$version
	Icarus Verilog
$end
$timescale
	1s
$end
$scope module blinkers $end
$var wire 1 ! clk $end
$var wire 1 " rstbtn $end
$var reg 4 # LED_1_BLINK_INTERVAL [3:0] $end
$var reg 4 $ LED_2_BLINK_INTERVAL [3:0] $end
$var reg 1 % clk_edge $end
$var reg 4 & cycle_count_led1 [3:0] $end
$var reg 4 ' cycle_count_led2 [3:0] $end
$var reg 1 ( led1 $end
$var reg 1 ) led2 $end
$var reg 1 * led3 $end
$scope task cycle_led $end
$var reg 4 + blink_interval [3:0] $end
$var reg 4 , cycle_count [3:0] $end
$var reg 1 - led $end
$upscope $end
$upscope $end
$enddefinitions $end
$comment Show the parameter values. $end
$dumpall
$end
#0
$dumpvars
x-
bx ,
bx +
0*
x)
x(
b0 '
b0 &
0%
b101 $
b1010 #
z"
z!
$end
#11
1)
1(
1-
b0 ,
b101 +
1%
#22
0%
#33
b101 +
1%
#44
0%
#55
b101 +
1%
#66
0%
#77
b101 +
1%
#88
0%
#99
b101 +
1%
#110
0%
#121
b101 +
1%
#132
0%
#143
b101 +
1%
#154
0%
#165
b101 +
1%
#176
0%
#187
b101 +
1%
#198
0%
#209
b101 +
1%
#220
0%
#231
b101 +
1%
#242
0%
#253
b101 +
1%
#264
0%
#275
b101 +
1%
#286
0%
#297
b101 +
1%
#308
0%
#319
b101 +
1%
#330
0%
#341
b101 +
1%
#352
0%
#363
b101 +
1%
#374
0%
#385
b101 +
1%
#396
0%
#407
b101 +
1%
#418
0%
#429
b101 +
1%
#440
0%
#451
b101 +
1%
#462
0%
#473
b101 +
1%
#484
0%
#495
b101 +
1%
#506
0%
#517
b101 +
1%
#528
0%
#539
b101 +
1%
#550
0%
#561
b101 +
1%
#572
0%
#583
b101 +
1%
#594
0%
#605
b101 +
1%
#616
0%
#627
b101 +
1%
#638
0%
#649
b101 +
1%
#660
0%
#671
b101 +
1%
#682
0%
#693
b101 +
1%
#704
0%
#715
b101 +
1%
#726
0%
#737
b101 +
1%
#748
0%
#759
b101 +
1%
#770
0%
#781
b101 +
1%
#792
0%
#803
b101 +
1%
#814
0%
#825
b101 +
1%
#836
0%
#847
b101 +
1%
#858
0%
#869
b101 +
1%
#880
0%
#891
b101 +
1%
#902
0%
#913
b101 +
1%
#924
0%
#935
b101 +
1%
#946
0%
#957
b101 +
1%
#968
0%
#979
b101 +
1%
