simulation/network.v
module network (
        input d,
        input clk,
        input rstn
    );
    initial begin
        $display("Welcome to the network mod, %d, %d, %rstn", d, clk, rstn);
    end
endmodule

simulation/test.v
module test(
        input d,
        input clk,
        input rstn
    );

    network n1(.d (d), .clk (clk), .rstn (rstn));

    parameter DATA_WIDTH = 8; // Example: 8-bit signals
    parameter MEM_DEPTH = 100; // Example: 100 samples

    // Declare a memory to store the signal data
    reg [DATA_WIDTH-1:0] signal_memory [0:MEM_DEPTH-1];    
    logic [DATA_WIDTH-1:0] current_signal;

    integer i;

    initial begin
        $dumpfile("../vcd/test.vcd");
        $dumpvars(0, test);

        $readmemb("../input/8wire.txt", signal_memory);

        // Example of how you might use the data over time
        for (i = 0; i < MEM_DEPTH; i = i + 1) begin
            current_signal = signal_memory[i];
            #10 if (current_signal !== 'x) begin
                $display("Time %0t: \n\t\tSignal = %b", $time, current_signal);
                $display("\t\tSignal[0] = %b", current_signal[0]);
            end 
        end
        $display("Hello, World");

        $finish ;
    end

endmodule

vcd/test.vcd
$date
	Mon Jul 14 12:43:41 2025
$end
$version
	Icarus Verilog
$end
$timescale
	1s
$end
$scope module test $end
$var wire 1 ! clk $end
$var wire 1 " d $end
$var wire 1 # rstn $end
$var parameter 32 $ DATA_WIDTH $end
$var parameter 32 % MEM_DEPTH $end
$var reg 8 & current_signal [7:0] $end
$var integer 32 ' i [31:0] $end
$scope module n1 $end
$var wire 1 ! clk $end
$var wire 1 " d $end
$var wire 1 # rstn $end
$upscope $end
$upscope $end
$enddefinitions $end
$comment Show the parameter values. $end
$dumpall
b1100100 %
b1000 $
$end
#0
$dumpvars
b0 '
b1010 &
z#
z"
z!
$end
#10
b10101 &
b1 '
#20
b101010 &
b10 '
#30
b110011 &
b11 '
#40
b1001100 &
b100 '
#50
bx &
b101 '
#60
b110 '
#70
b111 '
#80
b1000 '
#90
b1001 '
#100
b1010 '
#110
b1011 '
#120
b1100 '
#130
b1101 '
#140
b1110 '
#150
b1111 '
#160
b10000 '
#170
b10001 '
#180
b10010 '
#190
b10011 '
#200
b10100 '
#210
b10101 '
#220
b10110 '
#230
b10111 '
#240
b11000 '
#250
b11001 '
#260
b11010 '
#270
b11011 '
#280
b11100 '
#290
b11101 '
#300
b11110 '
#310
b11111 '
#320
b100000 '
#330
b100001 '
#340
b100010 '
#350
b100011 '
#360
b100100 '
#370
b100101 '
#380
b100110 '
#390
b100111 '
#400
b101000 '
#410
b101001 '
#420
b101010 '
#430
b101011 '
#440
b101100 '
#450
b101101 '
#460
b101110 '
#470
b101111 '
#480
b110000 '
#490
b110001 '
#500
b110010 '
#510
b110011 '
#520
b110100 '
#530
b110101 '
#540
b110110 '
#550
b110111 '
#560
b111000 '
#570
b111001 '
#580
b111010 '
#590
b111011 '
#600
b111100 '
#610
b111101 '
#620
b111110 '
#630
b111111 '
#640
b1000000 '
#650
b1000001 '
#660
b1000010 '
#670
b1000011 '
#680
b1000100 '
#690
b1000101 '
#700
b1000110 '
#710
b1000111 '
#720
b1001000 '
#730
b1001001 '
#740
b1001010 '
#750
b1001011 '
#760
b1001100 '
#770
b1001101 '
#780
b1001110 '
#790
b1001111 '
#800
b1010000 '
#810
b1010001 '
#820
b1010010 '
#830
b1010011 '
#840
b1010100 '
#850
b1010101 '
#860
b1010110 '
#870
b1010111 '
#880
b1011000 '
#890
b1011001 '
#900
b1011010 '
#910
b1011011 '
#920
b1011100 '
#930
b1011101 '
#940
b1011110 '
#950
b1011111 '
#960
b1100000 '
#970
b1100001 '
#980
b1100010 '
#990
b1100011 '
#1000
b1100100 '
