mini_projects/blinker/blinkers.v
/*
This module is meant as a way for me to learn some basic Verilog and have an 
easily verifiable test bench.

The idea is that 3 LEDs are on a chip
LED 1 : Blink every 10 cycles
LED 2 : Blink every 5 cycles
LED 3 : Blink every <random_interval> cycles
        Since verilog does not synthesize $random, one needs to implement a 
        LFSR to get a random value
        https://en.wikipedia.org/wiki/Linear-feedback_shift_register
        https://simplefpga.blogspot.com/2013/02/random-number-generator-in-verilog-fpga.html
*/
module blinkers (
    input clk,
    input rstbtn,
    output reg led1 = 0, led2 = 0, led3 = 0
);

    reg clk_edge = 0;
    wire [4:0] random_interval ;
    LFSR lfsr_calc(clk_edge, rstbtn, random_interval);
    assign is_undefined_byte = (random_interval == 5'bx);

    initial begin
        $dumpfile("./blinkers.vcd");
        $dumpvars(0, blinkers);
        // $monitor("Random Interval Update: %b", random_interval);
        // $monitor("LED 3 Interval Update: %b", LED_3_BLINK_INTERVAL);
        #10000 $finish;
    end

    always #10 begin 
        clk_edge = ~clk_edge;
    end

    reg [3:0] cycle_count_led1 = 'b0;
    reg [3:0] cycle_count_led2 = 'b0;
    reg [3:0] cycle_count_led3 = 'b0;

    reg [3:0] LED_1_BLINK_INTERVAL = 'b1001; // 9
    reg [3:0] LED_2_BLINK_INTERVAL = 'b0100; // 4
    reg [3:0] LED_3_BLINK_INTERVAL = 'b1111; // Cycle after first run to immediately get new value

    task cycle_led (
        output led,
        input reg [3:0] blink_interval,
        inout reg [3:0] cycle_count
    );
        if (cycle_count > 0 && cycle_count % blink_interval == 0) begin
            cycle_count = 0;
            led = 1;
        end else begin
            cycle_count += 1;
            led = 0;
        end
    endtask

    always @(posedge clk_edge, negedge clk_edge, posedge rstbtn) begin
        if (rstbtn) begin 
            led1 <= 0;
            led2 <= 0;
            led3 <= 0;
            cycle_count_led1 <= 0;
            cycle_count_led2 <= 0;
        end else begin 
            cycle_led(led1, LED_1_BLINK_INTERVAL, cycle_count_led1);
            cycle_led(led2, LED_2_BLINK_INTERVAL, cycle_count_led2);
            // cycle_led(led3, LED_3_BLINK_INTERVAL[3:0], cycle_count_led3);
            if (cycle_count_led3 > 0 && cycle_count_led3 % LED_3_BLINK_INTERVAL == 0) begin
                cycle_count_led3 <= 0;
                led3 <= 1;
                if (random_interval !== 5'bx && random_interval[3:0] !== 'b0) begin 
                    LED_3_BLINK_INTERVAL <= random_interval[3:0]; // remove largest bit
                end
                // $display("RANDOM_INTERVAL: %d, %d, %d", random_interval, is_undefined_byte, random_interval === 5'bx);
            end else begin
                cycle_count_led3 <= cycle_count_led3 + 1;
                led3 <= 0;
            end
        end
    end
endmodule

module LFSR (
    clk,
    rst,
    rnd 
);
    parameter RANDOM_BIT_LENGTH = 5; // >= 5
    output [4:0] rnd;
    input clk, rst;
    wire feedback = random[RANDOM_BIT_LENGTH-1] ^ random[3] ^ random[2] ^ random[0]; 
    reg [RANDOM_BIT_LENGTH-1:0] random = 'b1, random_next, random_done;
    reg [3:0] count = 0, count_next; //to keep track of the shifts

    always @ (posedge clk or posedge rst) begin
        if (rst) begin
            random <= 'b1; //An LFSR cannot have an all 0 state, thus rst to full
            count <= 0;
        end else begin
            random <= random_next;
            count <= count_next;
        end
        // $display("random: %d count: %d, random_next: %d, count_next: %d, feedback: %d", random, count, random_next, count_next, feedback);
    end

    always @ (*) begin
        random_next = random; //default state stays the same
        count_next = count;

        random_next = {random[RANDOM_BIT_LENGTH-2:0], feedback}; //shift left the xor'd every posedgeclk 
        count_next = count + 1;

        if (count == RANDOM_BIT_LENGTH) begin
            count = 0;
            random_done = random; //assign the random number to output after RANDOM_BIT_LENGTH shifts
        end
    end
    
    assign rnd = random_done;
endmodule

mini_projects/blinker/blinkers.vcd
$date
	Wed Jul 23 10:42:08 2025
$end
$version
	Icarus Verilog
$end
$timescale
	1s
$end
$scope module blinkers $end
$var wire 1 ! clk $end
$var wire 1 " rstbtn $end
$var wire 5 # random_interval [4:0] $end
$var wire 1 $ is_undefined_byte $end
$var reg 4 % LED_1_BLINK_INTERVAL [3:0] $end
$var reg 4 & LED_2_BLINK_INTERVAL [3:0] $end
$var reg 4 ' LED_3_BLINK_INTERVAL [3:0] $end
$var reg 1 ( clk_edge $end
$var reg 4 ) cycle_count_led1 [3:0] $end
$var reg 4 * cycle_count_led2 [3:0] $end
$var reg 4 + cycle_count_led3 [3:0] $end
$var reg 1 , led1 $end
$var reg 1 - led2 $end
$var reg 1 . led3 $end
$scope module lfsr_calc $end
$var wire 1 ( clk $end
$var wire 1 / feedback $end
$var wire 5 0 rnd [4:0] $end
$var wire 1 " rst $end
$var parameter 32 1 RANDOM_BIT_LENGTH $end
$var reg 4 2 count [3:0] $end
$var reg 4 3 count_next [3:0] $end
$var reg 5 4 random [4:0] $end
$var reg 5 5 random_done [4:0] $end
$var reg 5 6 random_next [4:0] $end
$upscope $end
$scope task cycle_led $end
$var reg 4 7 blink_interval [3:0] $end
$var reg 4 8 cycle_count [3:0] $end
$var reg 1 9 led $end
$upscope $end
$upscope $end
$enddefinitions $end
$comment Show the parameter values. $end
$dumpall
b101 1
$end
#0
$dumpvars
x9
bx 8
bx 7
b11 6
bx 5
b1 4
b1 3
b0 2
bx 0
1/
0.
0-
0,
b0 +
b0 *
b0 )
0(
b1111 '
b100 &
b1001 %
x$
bx #
z"
z!
$end
#10
b10 3
b111 6
b1 2
b11 4
b1 +
b1 *
b1 )
09
b1 8
b100 7
1(
#20
b10 +
b10 *
b10 )
b10 8
b100 7
0(
#30
0/
b11 3
b1110 6
b10 2
b111 4
b11 +
b11 *
b11 )
b11 8
b100 7
1(
#40
b100 +
b100 *
b100 )
b100 8
b100 7
0(
#50
0/
b100 3
b11100 6
b11 2
b1110 4
b101 +
b0 *
1-
19
b101 )
b0 8
b100 7
1(
#60
b110 +
b1 *
0-
b110 )
09
b1 8
b100 7
0(
#70
1/
b101 3
b11001 6
b100 2
b11100 4
b111 +
b10 *
b111 )
b10 8
b100 7
1(
#80
b1000 +
b11 *
b1000 )
b11 8
b100 7
0(
#90
1/
b11001 #
b11001 0
b11001 5
b1 3
b10011 6
b0 2
b11001 4
b1001 +
b100 *
b1001 )
b100 8
b100 7
1(
#100
b1010 +
b0 *
1-
b0 )
1,
19
b0 8
b100 7
0(
#110
0/
b10 3
b110 6
b1 2
b10011 4
b1011 +
b1 *
0-
b1 )
0,
09
b1 8
b100 7
1(
#120
b1100 +
b10 *
b10 )
b10 8
b100 7
0(
#130
1/
b11 3
b1101 6
b10 2
b110 4
b1101 +
b11 *
b11 )
b11 8
b100 7
1(
#140
b1110 +
b100 *
b100 )
b100 8
b100 7
0(
#150
1/
b100 3
b11011 6
b11 2
b1101 4
b1111 +
b0 *
1-
19
b101 )
b0 8
b100 7
1(
#160
b1001 '
1.
b0 +
b1 *
0-
b110 )
09
b1 8
b100 7
0(
#170
1/
b101 3
b10111 6
b100 2
b11011 4
0.
b1 +
b10 *
b111 )
b10 8
b100 7
1(
#180
b10 +
b11 *
b1000 )
b11 8
b100 7
0(
#190
1/
b10111 #
b10111 0
b10111 5
b1 3
b1111 6
b0 2
b10111 4
b11 +
b100 *
b1001 )
b100 8
b100 7
1(
#200
b100 +
b0 *
1-
b0 )
1,
19
b0 8
b100 7
0(
#210
b10 3
b11111 6
b1 2
b1111 4
b101 +
b1 *
0-
b1 )
0,
09
b1 8
b100 7
1(
#220
b110 +
b10 *
b10 )
b10 8
b100 7
0(
#230
b11110 6
0/
b11 3
b10 2
b11111 4
b111 +
b11 *
b11 )
b11 8
b100 7
1(
#240
b1000 +
b100 *
b100 )
b100 8
b100 7
0(
#250
1/
b100 3
b11101 6
b11 2
b11110 4
b1001 +
b0 *
1-
19
b101 )
b0 8
b100 7
1(
#260
b111 '
1.
b0 +
b1 *
0-
b110 )
09
b1 8
b100 7
0(
#270
0/
b101 3
b11010 6
b100 2
b11101 4
0.
b1 +
b10 *
b111 )
b10 8
b100 7
1(
#280
b10 +
b11 *
b1000 )
b11 8
b100 7
0(
#290
0/
b11010 #
b11010 0
b11010 5
b1 3
b10100 6
b0 2
b11010 4
b11 +
b100 *
b1001 )
b100 8
b100 7
1(
#300
b100 +
b0 *
1-
b0 )
1,
19
b0 8
b100 7
0(
#310
0/
b10 3
b1000 6
b1 2
b10100 4
b101 +
b1 *
0-
b1 )
0,
09
b1 8
b100 7
1(
#320
b110 +
b10 *
b10 )
b10 8
b100 7
0(
#330
1/
b11 3
b10001 6
b10 2
b1000 4
b111 +
b11 *
b11 )
b11 8
b100 7
1(
#340
b1010 '
1.
b0 +
b100 *
b100 )
b100 8
b100 7
0(
#350
0/
b100 3
b10 6
b11 2
b10001 4
0.
b1 +
b0 *
1-
19
b101 )
b0 8
b100 7
1(
#360
b10 +
b1 *
0-
b110 )
09
b1 8
b100 7
0(
#370
0/
b101 3
b100 6
b100 2
b10 4
b11 +
b10 *
b111 )
b10 8
b100 7
1(
#380
b100 +
b11 *
b1000 )
b11 8
b100 7
0(
#390
1/
b100 #
b100 0
b100 5
b1 3
b1001 6
b0 2
b100 4
b101 +
b100 *
b1001 )
b100 8
b100 7
1(
#400
b110 +
b0 *
1-
b0 )
1,
19
b0 8
b100 7
0(
#410
0/
b10 3
b10010 6
b1 2
b1001 4
b111 +
b1 *
0-
b1 )
0,
09
b1 8
b100 7
1(
#420
b1000 +
b10 *
b10 )
b10 8
b100 7
0(
#430
1/
b11 3
b101 6
b10 2
b10010 4
b1001 +
b11 *
b11 )
b11 8
b100 7
1(
#440
b1010 +
b100 *
b100 )
b100 8
b100 7
0(
#450
0/
b100 3
b1010 6
b11 2
b101 4
b100 '
1.
b0 +
b0 *
1-
19
b101 )
b0 8
b100 7
1(
#460
0.
b1 +
b1 *
0-
b110 )
09
b1 8
b100 7
0(
#470
1/
b101 3
b10101 6
b100 2
b1010 4
b10 +
b10 *
b111 )
b10 8
b100 7
1(
#480
b11 +
b11 *
b1000 )
b11 8
b100 7
0(
#490
1/
b10101 #
b10101 0
b10101 5
b1 3
b1011 6
b0 2
b10101 4
b100 +
b100 *
b1001 )
b100 8
b100 7
1(
#500
b101 '
1.
b0 +
b0 *
1-
b0 )
1,
19
b0 8
b100 7
0(
#510
0/
b10 3
b10110 6
b1 2
b1011 4
0.
b1 +
b1 *
0-
b1 )
0,
09
b1 8
b100 7
1(
#520
b10 +
b10 *
b10 )
b10 8
b100 7
0(
#530
0/
b11 3
b1100 6
b10 2
b10110 4
b11 +
b11 *
b11 )
b11 8
b100 7
1(
#540
b100 +
b100 *
b100 )
b100 8
b100 7
0(
#550
b100 3
b11000 6
b11 2
b1100 4
b101 +
b0 *
1-
19
b101 )
b0 8
b100 7
1(
#560
1.
b0 +
b1 *
0-
b110 )
09
b1 8
b100 7
0(
#570
0/
b101 3
b10000 6
b100 2
b11000 4
0.
b1 +
b10 *
b111 )
b10 8
b100 7
1(
#580
b10 +
b11 *
b1000 )
b11 8
b100 7
0(
#590
1/
b10000 #
b10000 0
b10000 5
b1 3
b1 6
b0 2
b10000 4
b11 +
b100 *
b1001 )
b100 8
b100 7
1(
#600
b100 +
b0 *
1-
b0 )
1,
19
b0 8
b100 7
0(
#610
1/
b10 3
b11 6
b1 2
b1 4
b101 +
b1 *
0-
b1 )
0,
09
b1 8
b100 7
1(
#620
1.
b0 +
b10 *
b10 )
b10 8
b100 7
0(
#630
b11 3
b111 6
b10 2
b11 4
0.
b1 +
b11 *
b11 )
b11 8
b100 7
1(
#640
b10 +
b100 *
b100 )
b100 8
b100 7
0(
#650
0/
b100 3
b1110 6
b11 2
b111 4
b11 +
b0 *
1-
19
b101 )
b0 8
b100 7
1(
#660
b100 +
b1 *
0-
b110 )
09
b1 8
b100 7
0(
#670
0/
b101 3
b11100 6
b100 2
b1110 4
b101 +
b10 *
b111 )
b10 8
b100 7
1(
#680
1.
b0 +
b11 *
b1000 )
b11 8
b100 7
0(
#690
1/
b11100 #
b11100 0
b11100 5
b1 3
b11001 6
b0 2
b11100 4
0.
b1 +
b100 *
b1001 )
b100 8
b100 7
1(
#700
b10 +
b0 *
1-
b0 )
1,
19
b0 8
b100 7
0(
#710
1/
b10 3
b10011 6
b1 2
b11001 4
b11 +
b1 *
0-
b1 )
0,
09
b1 8
b100 7
1(
#720
b100 +
b10 *
b10 )
b10 8
b100 7
0(
#730
0/
b11 3
b110 6
b10 2
b10011 4
b101 +
b11 *
b11 )
b11 8
b100 7
1(
#740
b1100 '
1.
b0 +
b100 *
b100 )
b100 8
b100 7
0(
#750
1/
b100 3
b1101 6
b11 2
b110 4
0.
b1 +
b0 *
1-
19
b101 )
b0 8
b100 7
1(
#760
b10 +
b1 *
0-
b110 )
09
b1 8
b100 7
0(
#770
1/
b101 3
b11011 6
b100 2
b1101 4
b11 +
b10 *
b111 )
b10 8
b100 7
1(
#780
b100 +
b11 *
b1000 )
b11 8
b100 7
0(
#790
1/
b11011 #
b11011 0
b11011 5
b1 3
b10111 6
b0 2
b11011 4
b101 +
b100 *
b1001 )
b100 8
b100 7
1(
#800
b110 +
b0 *
1-
b0 )
1,
19
b0 8
b100 7
0(
#810
1/
b10 3
b1111 6
b1 2
b10111 4
b111 +
b1 *
0-
b1 )
0,
09
b1 8
b100 7
1(
#820
b1000 +
b10 *
b10 )
b10 8
b100 7
0(
#830
b11 3
b11111 6
b10 2
b1111 4
b1001 +
b11 *
b11 )
b11 8
b100 7
1(
#840
b1010 +
b100 *
b100 )
b100 8
b100 7
0(
#850
b11110 6
0/
b100 3
b11 2
b11111 4
b1011 +
b0 *
1-
19
b101 )
b0 8
b100 7
1(
#860
b1100 +
b1 *
0-
b110 )
09
b1 8
b100 7
0(
#870
1/
b101 3
b11101 6
b100 2
b11110 4
b1011 '
1.
b0 +
b10 *
b111 )
b10 8
b100 7
1(
#880
0.
b1 +
b11 *
b1000 )
b11 8
b100 7
0(
#890
0/
b11101 #
b11101 0
b11101 5
b1 3
b11010 6
b0 2
b11101 4
b10 +
b100 *
b1001 )
b100 8
b100 7
1(
#900
b11 +
b0 *
1-
b0 )
1,
19
b0 8
b100 7
0(
#910
0/
b10 3
b10100 6
b1 2
b11010 4
b100 +
b1 *
0-
b1 )
0,
09
b1 8
b100 7
1(
#920
b101 +
b10 *
b10 )
b10 8
b100 7
0(
#930
0/
b11 3
b1000 6
b10 2
b10100 4
b110 +
b11 *
b11 )
b11 8
b100 7
1(
#940
b111 +
b100 *
b100 )
b100 8
b100 7
0(
#950
1/
b100 3
b10001 6
b11 2
b1000 4
b1000 +
b0 *
1-
19
b101 )
b0 8
b100 7
1(
#960
b1001 +
b1 *
0-
b110 )
09
b1 8
b100 7
0(
#970
0/
b101 3
b10 6
b100 2
b10001 4
b1010 +
b10 *
b111 )
b10 8
b100 7
1(
#980
b1011 +
b11 *
b1000 )
b11 8
b100 7
0(
#990
0/
b10 #
b10 0
b10 5
b1 3
b100 6
b0 2
b10 4
b1101 '
1.
b0 +
b100 *
b1001 )
b100 8
b100 7
1(
#1000
0.
b1 +
b0 *
1-
b0 )
1,
19
b0 8
b100 7
0(
#1010
1/
b10 3
b1001 6
b1 2
b100 4
b10 +
b1 *
0-
b1 )
0,
09
b1 8
b100 7
1(
#1020
b11 +
b10 *
b10 )
b10 8
b100 7
0(
#1030
0/
b11 3
b10010 6
b10 2
b1001 4
b100 +
b11 *
b11 )
b11 8
b100 7
1(
#1040
b101 +
b100 *
b100 )
b100 8
b100 7
0(
#1050
1/
b100 3
b101 6
b11 2
b10010 4
b110 +
b0 *
1-
19
b101 )
b0 8
b100 7
1(
#1060
b111 +
b1 *
0-
b110 )
09
b1 8
b100 7
0(
#1070
0/
b101 3
b1010 6
b100 2
b101 4
b1000 +
b10 *
b111 )
b10 8
b100 7
1(
#1080
b1001 +
b11 *
b1000 )
b11 8
b100 7
0(
#1090
1/
b1010 #
b1010 0
b1010 5
b1 3
b10101 6
b0 2
b1010 4
b1010 +
b100 *
b1001 )
b100 8
b100 7
1(
#1100
b1011 +
b0 *
1-
b0 )
1,
19
b0 8
b100 7
0(
#1110
1/
b10 3
b1011 6
b1 2
b10101 4
b1100 +
b1 *
0-
b1 )
0,
09
b1 8
b100 7
1(
#1120
b1101 +
b10 *
b10 )
b10 8
b100 7
0(
#1130
0/
b11 3
b10110 6
b10 2
b1011 4
b1010 '
1.
b0 +
b11 *
b11 )
b11 8
b100 7
1(
#1140
0.
b1 +
b100 *
b100 )
b100 8
b100 7
0(
#1150
0/
b100 3
b1100 6
b11 2
b10110 4
b10 +
b0 *
1-
19
b101 )
b0 8
b100 7
1(
#1160
b11 +
b1 *
0-
b110 )
09
b1 8
b100 7
0(
#1170
b101 3
b11000 6
b100 2
b1100 4
b100 +
b10 *
b111 )
b10 8
b100 7
1(
#1180
b101 +
b11 *
b1000 )
b11 8
b100 7
0(
#1190
0/
b11000 #
b11000 0
b11000 5
b1 3
b10000 6
b0 2
b11000 4
b110 +
b100 *
b1001 )
b100 8
b100 7
1(
#1200
b111 +
b0 *
1-
b0 )
1,
19
b0 8
b100 7
0(
#1210
1/
b10 3
b1 6
b1 2
b10000 4
b1000 +
b1 *
0-
b1 )
0,
09
b1 8
b100 7
1(
#1220
b1001 +
b10 *
b10 )
b10 8
b100 7
0(
#1230
1/
b11 3
b11 6
b10 2
b1 4
b1010 +
b11 *
b11 )
b11 8
b100 7
1(
#1240
b1000 '
1.
b0 +
b100 *
b100 )
b100 8
b100 7
0(
#1250
b100 3
b111 6
b11 2
b11 4
0.
b1 +
b0 *
1-
19
b101 )
b0 8
b100 7
1(
#1260
b10 +
b1 *
0-
b110 )
09
b1 8
b100 7
0(
#1270
0/
b101 3
b1110 6
b100 2
b111 4
b11 +
b10 *
b111 )
b10 8
b100 7
1(
#1280
b100 +
b11 *
b1000 )
b11 8
b100 7
0(
#1290
0/
b1110 #
b1110 0
b1110 5
b1 3
b11100 6
b0 2
b1110 4
b101 +
b100 *
b1001 )
b100 8
b100 7
1(
#1300
b110 +
b0 *
1-
b0 )
1,
19
b0 8
b100 7
0(
#1310
1/
b10 3
b11001 6
b1 2
b11100 4
b111 +
b1 *
0-
b1 )
0,
09
b1 8
b100 7
1(
#1320
b1000 +
b10 *
b10 )
b10 8
b100 7
0(
#1330
1/
b11 3
b10011 6
b10 2
b11001 4
b1110 '
1.
b0 +
b11 *
b11 )
b11 8
b100 7
1(
#1340
0.
b1 +
b100 *
b100 )
b100 8
b100 7
0(
#1350
0/
b100 3
b110 6
b11 2
b10011 4
b10 +
b0 *
1-
19
b101 )
b0 8
b100 7
1(
#1360
b11 +
b1 *
0-
b110 )
09
b1 8
b100 7
0(
#1370
1/
b101 3
b1101 6
b100 2
b110 4
b100 +
b10 *
b111 )
b10 8
b100 7
1(
#1380
b101 +
b11 *
b1000 )
b11 8
b100 7
0(
#1390
1/
b1101 #
b1101 0
b1101 5
b1 3
b11011 6
b0 2
b1101 4
b110 +
b100 *
b1001 )
b100 8
b100 7
1(
#1400
b111 +
b0 *
1-
b0 )
1,
19
b0 8
b100 7
0(
#1410
1/
b10 3
b10111 6
b1 2
b11011 4
b1000 +
b1 *
0-
b1 )
0,
09
b1 8
b100 7
1(
#1420
b1001 +
b10 *
b10 )
b10 8
b100 7
0(
#1430
1/
b11 3
b1111 6
b10 2
b10111 4
b1010 +
b11 *
b11 )
b11 8
b100 7
1(
#1440
b1011 +
b100 *
b100 )
b100 8
b100 7
0(
#1450
b100 3
b11111 6
b11 2
b1111 4
b1100 +
b0 *
1-
19
b101 )
b0 8
b100 7
1(
#1460
b1101 +
b1 *
0-
b110 )
09
b1 8
b100 7
0(
#1470
b11110 6
0/
b101 3
b100 2
b11111 4
b1110 +
b10 *
b111 )
b10 8
b100 7
1(
#1480
b1101 '
1.
b0 +
b11 *
b1000 )
b11 8
b100 7
0(
#1490
1/
b11110 #
b11110 0
b11110 5
b1 3
b11101 6
b0 2
b11110 4
0.
b1 +
b100 *
b1001 )
b100 8
b100 7
1(
#1500
b10 +
b0 *
1-
b0 )
1,
19
b0 8
b100 7
0(
#1510
0/
b10 3
b11010 6
b1 2
b11101 4
b11 +
b1 *
0-
b1 )
0,
09
b1 8
b100 7
1(
#1520
b100 +
b10 *
b10 )
b10 8
b100 7
0(
#1530
0/
b11 3
b10100 6
b10 2
b11010 4
b101 +
b11 *
b11 )
b11 8
b100 7
1(
#1540
b110 +
b100 *
b100 )
b100 8
b100 7
0(
#1550
0/
b100 3
b1000 6
b11 2
b10100 4
b111 +
b0 *
1-
19
b101 )
b0 8
b100 7
1(
#1560
b1000 +
b1 *
0-
b110 )
09
b1 8
b100 7
0(
#1570
1/
b101 3
b10001 6
b100 2
b1000 4
b1001 +
b10 *
b111 )
b10 8
b100 7
1(
#1580
b1010 +
b11 *
b1000 )
b11 8
b100 7
0(
#1590
0/
b10001 #
b10001 0
b10001 5
b1 3
b10 6
b0 2
b10001 4
b1011 +
b100 *
b1001 )
b100 8
b100 7
1(
#1600
b1100 +
b0 *
1-
b0 )
1,
19
b0 8
b100 7
0(
#1610
0/
b10 3
b100 6
b1 2
b10 4
b1101 +
b1 *
0-
b1 )
0,
09
b1 8
b100 7
1(
#1620
b1 '
1.
b0 +
b10 *
b10 )
b10 8
b100 7
0(
#1630
1/
b11 3
b1001 6
b10 2
b100 4
0.
b1 +
b11 *
b11 )
b11 8
b100 7
1(
#1640
1.
b0 +
b100 *
b100 )
b100 8
b100 7
0(
#1650
0/
b100 3
b10010 6
b11 2
b1001 4
0.
b1 +
b0 *
1-
19
b101 )
b0 8
b100 7
1(
#1660
1.
b0 +
b1 *
0-
b110 )
09
b1 8
b100 7
0(
#1670
1/
b101 3
b101 6
b100 2
b10010 4
0.
b1 +
b10 *
b111 )
b10 8
b100 7
1(
#1680
1.
b0 +
b11 *
b1000 )
b11 8
b100 7
0(
#1690
0/
b101 #
b101 0
b101 5
b1 3
b1010 6
b0 2
b101 4
0.
b1 +
b100 *
b1001 )
b100 8
b100 7
1(
#1700
b101 '
1.
b0 +
b0 *
1-
b0 )
1,
19
b0 8
b100 7
0(
#1710
1/
b10 3
b10101 6
b1 2
b1010 4
0.
b1 +
b1 *
0-
b1 )
0,
09
b1 8
b100 7
1(
#1720
b10 +
b10 *
b10 )
b10 8
b100 7
0(
#1730
1/
b11 3
b1011 6
b10 2
b10101 4
b11 +
b11 *
b11 )
b11 8
b100 7
1(
#1740
b100 +
b100 *
b100 )
b100 8
b100 7
0(
#1750
0/
b100 3
b10110 6
b11 2
b1011 4
b101 +
b0 *
1-
19
b101 )
b0 8
b100 7
1(
#1760
1.
b0 +
b1 *
0-
b110 )
09
b1 8
b100 7
0(
#1770
0/
b101 3
b1100 6
b100 2
b10110 4
0.
b1 +
b10 *
b111 )
b10 8
b100 7
1(
#1780
b10 +
b11 *
b1000 )
b11 8
b100 7
0(
#1790
b1100 #
b1100 0
b1100 5
b110 3
b11000 6
b0 2
b1100 4
b11 +
b100 *
b1001 )
b100 8
b100 7
1(
#1800
b100 +
b0 *
1-
b0 )
1,
19
b0 8
b100 7
0(
#1810
0/
b111 3
b10000 6
b110 2
b11000 4
b101 +
b1 *
0-
b1 )
0,
09
b1 8
b100 7
1(
#1820
b1100 '
1.
b0 +
b10 *
b10 )
b10 8
b100 7
0(
#1830
1/
b1000 3
b1 6
b111 2
b10000 4
0.
b1 +
b11 *
b11 )
b11 8
b100 7
1(
#1840
b10 +
b100 *
b100 )
b100 8
b100 7
0(
#1850
1/
b1001 3
b11 6
b1000 2
b1 4
b11 +
b0 *
1-
19
b101 )
b0 8
b100 7
1(
#1860
b100 +
b1 *
0-
b110 )
09
b1 8
b100 7
0(
#1870
b1010 3
b111 6
b1001 2
b11 4
b101 +
b10 *
b111 )
b10 8
b100 7
1(
#1880
b110 +
b11 *
b1000 )
b11 8
b100 7
0(
#1890
0/
b1011 3
b1110 6
b1010 2
b111 4
b111 +
b100 *
b1001 )
b100 8
b100 7
1(
#1900
b1000 +
b0 *
1-
b0 )
1,
19
b0 8
b100 7
0(
#1910
0/
b1100 3
b11100 6
b1011 2
b1110 4
b1001 +
b1 *
0-
b1 )
0,
09
b1 8
b100 7
1(
#1920
b1010 +
b10 *
b10 )
b10 8
b100 7
0(
#1930
1/
b1101 3
b11001 6
b1100 2
b11100 4
b1011 +
b11 *
b11 )
b11 8
b100 7
1(
#1940
b1100 +
b100 *
b100 )
b100 8
b100 7
0(
#1950
1/
b1110 3
b10011 6
b1101 2
b11001 4
1.
b0 +
b0 *
1-
19
b101 )
b0 8
b100 7
1(
#1960
0.
b1 +
b1 *
0-
b110 )
09
b1 8
b100 7
0(
#1970
0/
b1111 3
b110 6
b1110 2
b10011 4
b10 +
b10 *
b111 )
b10 8
b100 7
1(
#1980
b11 +
b11 *
b1000 )
b11 8
b100 7
0(
#1990
1/
b0 3
b1101 6
b1111 2
b110 4
b100 +
b100 *
b1001 )
b100 8
b100 7
1(
#2000
b101 +
b0 *
1-
b0 )
1,
19
b0 8
b100 7
0(
#2010
1/
b1 3
b11011 6
b0 2
b1101 4
b110 +
b1 *
0-
b1 )
0,
09
b1 8
b100 7
1(
#2020
b111 +
b10 *
b10 )
b10 8
b100 7
0(
#2030
1/
b10 3
b10111 6
b1 2
b11011 4
b1000 +
b11 *
b11 )
b11 8
b100 7
1(
#2040
b1001 +
b100 *
b100 )
b100 8
b100 7
0(
#2050
1/
b11 3
b1111 6
b10 2
b10111 4
b1010 +
b0 *
1-
19
b101 )
b0 8
b100 7
1(
#2060
b1011 +
b1 *
0-
b110 )
09
b1 8
b100 7
0(
#2070
b100 3
b11111 6
b11 2
b1111 4
b1100 +
b10 *
b111 )
b10 8
b100 7
1(
#2080
1.
b0 +
b11 *
b1000 )
b11 8
b100 7
0(
#2090
b11110 6
0/
b101 3
b100 2
b11111 4
0.
b1 +
b100 *
b1001 )
b100 8
b100 7
1(
#2100
b10 +
b0 *
1-
b0 )
1,
19
b0 8
b100 7
0(
#2110
1/
b11110 #
b11110 0
b11110 5
b1 3
b11101 6
b0 2
b11110 4
b11 +
b1 *
0-
b1 )
0,
09
b1 8
b100 7
1(
#2120
b100 +
b10 *
b10 )
b10 8
b100 7
0(
#2130
0/
b10 3
b11010 6
b1 2
b11101 4
b101 +
b11 *
b11 )
b11 8
b100 7
1(
#2140
b110 +
b100 *
b100 )
b100 8
b100 7
0(
#2150
0/
b11 3
b10100 6
b10 2
b11010 4
b111 +
b0 *
1-
19
b101 )
b0 8
b100 7
1(
#2160
b1000 +
b1 *
0-
b110 )
09
b1 8
b100 7
0(
#2170
0/
b100 3
b1000 6
b11 2
b10100 4
b1001 +
b10 *
b111 )
b10 8
b100 7
1(
#2180
b1010 +
b11 *
b1000 )
b11 8
b100 7
0(
#2190
1/
b101 3
b10001 6
b100 2
b1000 4
b1011 +
b100 *
b1001 )
b100 8
b100 7
1(
#2200
b1100 +
b0 *
1-
b0 )
1,
19
b0 8
b100 7
0(
#2210
0/
b10001 #
b10001 0
b10001 5
b1 3
b10 6
b0 2
b10001 4
b1110 '
1.
b0 +
b1 *
0-
b1 )
0,
09
b1 8
b100 7
1(
#2220
0.
b1 +
b10 *
b10 )
b10 8
b100 7
0(
#2230
0/
b10 3
b100 6
b1 2
b10 4
b10 +
b11 *
b11 )
b11 8
b100 7
1(
#2240
b11 +
b100 *
b100 )
b100 8
b100 7
0(
#2250
1/
b11 3
b1001 6
b10 2
b100 4
b100 +
b0 *
1-
19
b101 )
b0 8
b100 7
1(
#2260
b101 +
b1 *
0-
b110 )
09
b1 8
b100 7
0(
#2270
0/
b100 3
b10010 6
b11 2
b1001 4
b110 +
b10 *
b111 )
b10 8
b100 7
1(
#2280
b111 +
b11 *
b1000 )
b11 8
b100 7
0(
#2290
1/
b101 3
b101 6
b100 2
b10010 4
b1000 +
b100 *
b1001 )
b100 8
b100 7
1(
#2300
b1001 +
b0 *
1-
b0 )
1,
19
b0 8
b100 7
0(
#2310
0/
b101 #
b101 0
b101 5
b1 3
b1010 6
b0 2
b101 4
b1010 +
b1 *
0-
b1 )
0,
09
b1 8
b100 7
1(
#2320
b1011 +
b10 *
b10 )
b10 8
b100 7
0(
#2330
1/
b10 3
b10101 6
b1 2
b1010 4
b1100 +
b11 *
b11 )
b11 8
b100 7
1(
#2340
b1101 +
b100 *
b100 )
b100 8
b100 7
0(
#2350
1/
b11 3
b1011 6
b10 2
b10101 4
b1110 +
b0 *
1-
19
b101 )
b0 8
b100 7
1(
#2360
b101 '
1.
b0 +
b1 *
0-
b110 )
09
b1 8
b100 7
0(
#2370
0/
b100 3
b10110 6
b11 2
b1011 4
0.
b1 +
b10 *
b111 )
b10 8
b100 7
1(
#2380
b10 +
b11 *
b1000 )
b11 8
b100 7
0(
#2390
0/
b101 3
b1100 6
b100 2
b10110 4
b11 +
b100 *
b1001 )
b100 8
b100 7
1(
#2400
b100 +
b0 *
1-
b0 )
1,
19
b0 8
b100 7
0(
#2410
b1100 #
b1100 0
b1100 5
b110 3
b11000 6
b0 2
b1100 4
b101 +
b1 *
0-
b1 )
0,
09
b1 8
b100 7
1(
#2420
b1100 '
1.
b0 +
b10 *
b10 )
b10 8
b100 7
0(
#2430
0/
b111 3
b10000 6
b110 2
b11000 4
0.
b1 +
b11 *
b11 )
b11 8
b100 7
1(
#2440
b10 +
b100 *
b100 )
b100 8
b100 7
0(
#2450
1/
b1000 3
b1 6
b111 2
b10000 4
b11 +
b0 *
1-
19
b101 )
b0 8
b100 7
1(
#2460
b100 +
b1 *
0-
b110 )
09
b1 8
b100 7
0(
#2470
1/
b1001 3
b11 6
b1000 2
b1 4
b101 +
b10 *
b111 )
b10 8
b100 7
1(
#2480
b110 +
b11 *
b1000 )
b11 8
b100 7
0(
